nonebot_plugin_memory/__init__.py
nonebot_plugin_memory/chat.py
nonebot_plugin_memory/config.py
nonebot_plugin_memory/precipitate_knowledge.py
nonebot_plugin_memory-0.1.13.dist-info/WHEEL
nonebot_plugin_memory-0.1.13.dist-info/METADATA
nonebot_plugin_memory-0.1.13.dist-info/RECORD
