Metadata-Version: 2.3
Name: nonebot-plugin-memory
Version: 0.1.13
Summary: 对跟bot对话的每个人形成记忆，生成有趣的用户档案，用于下次生成回复，也可以通过指令查看已有的用户档案。
Author: lanxinmob
Author-email: lanxinmob <mobu54511@gmail.com>
Requires-Dist: nonebot2>=2.4.3,<3.0.0
Requires-Dist: nonebot-plugin-apscheduler>=0.5.0,<1.0.0
Requires-Dist: nonebot-adapter-onebot>=2.4.6,<3.0.0
Requires-Dist: redis>=5.0.0,<6.0.0
Requires-Dist: openai>=2.0.0
Requires-Python: >=3.10
Project-URL: Homepage, https://github.com/lanxinmob/nonebot-plugin-memory
Project-URL: Issues, https://github.com/lanxinmob/nonebot-plugin-memory/issues
Project-URL: Repository, https://github.com/lanxinmob/nonebot-plugin-memory.git
